fond_utils-0.1.6.dist-info/licenses/LICENSE
fondutils/__init__.py
fondutils/__main__.py
fondutils/determizer.py
fondutils/normalizer.py
fondutils/sas.py
fondutils/helpers/__init__.py
fondutils/helpers/base.py
fondutils/pddl/__init__.py
fondutils/pddl/domprob.lark
fondutils/pddl/domprob.py
fond_utils-0.1.6.dist-info/METADATA
fond_utils-0.1.6.dist-info/WHEEL
fond_utils-0.1.6.dist-info/entry_points.txt
fond_utils-0.1.6.dist-info/top_level.txt
fond_utils-0.1.6.dist-info/RECORD
