Metadata-Version: 2.4
Name: fond-utils
Version: 0.1.6
Summary: FOND Utilities and Helpers
Author-email: Christian Muise <christian.muise@queensu.ca>, Sebastian Sardina <ssardina@gmail.com>
License: MIT
Project-URL: Homepage, https://github.com/AI-Planning/fond-utils/
Classifier: Programming Language :: Python :: 3
Classifier: License :: OSI Approved :: MIT License
Classifier: Operating System :: POSIX :: Linux
Requires-Python: >=3.8
License-File: LICENSE
Requires-Dist: pddl
Dynamic: license-file
